Metadata-Version: 2.1
Name: ks-currency-convertor
Version: 0.0.1
Summary: A very currency convertor
Home-page: UNKNOWN
Author: Kripa Sindhu
Author-email: sindhukripa007@gmail.com
License: MIT
Keywords: currency_convertor
Platform: UNKNOWN
Classifier: Development Status :: 5 - Production/Stable
Classifier: Intended Audience :: Education
Classifier: Operating System :: Microsoft :: Windows :: Windows 10
Classifier: License :: OSI Approved :: MIT License
Classifier: Programming Language :: Python :: 3
License-File: LICENCE.txt
